ocr_translate_ollama/__init__.py
ocr_translate_ollama/commons.py
ocr_translate_ollama/plugin.py
ocr_translate_ollama/migrations/__init__.py
ocr_translate_ollama-0.3.0.dist-info/entry_points.txt
ocr_translate_ollama-0.3.0.dist-info/licenses/LICENSE.txt
ocr_translate_ollama-0.3.0.dist-info/WHEEL
ocr_translate_ollama-0.3.0.dist-info/METADATA
ocr_translate_ollama-0.3.0.dist-info/RECORD
