Metadata-Version: 2.4
Name: ocr_translate_ollama
Version: 0.3.0
Summary: Plugin to implement ollama (LLMs) based translations for ocr_translate
Keywords: django,translation
Requires-Python: >=3.10
Classifier: Programming Language :: Python
Classifier: Programming Language :: Python :: 3.10
License-File: LICENSE.txt
Requires-Dist: requests
Requires-Dist: django-ocr_translate>=0.7.0,<1.0
Requires-Dist: pre-commit ; extra == "pre-commit"
Requires-Dist: pylint ; extra == "pre-commit"
Requires-Dist: pylint-pytest ; extra == "pre-commit"
Requires-Dist: pylint-django ; extra == "pre-commit"
Requires-Dist: flit ; extra == "release"
Requires-Dist: pytest ; extra == "tests"
Requires-Dist: pytest-cov ; extra == "tests"
Requires-Dist: pytest-django ; extra == "tests"
Project-URL: Source, https://github.com/Crivella/ocr_translate-ollama
Provides-Extra: pre-commit
Provides-Extra: release
Provides-Extra: tests
